meili_ros_lib/__init__.py
meili_ros_lib/agent.py
meili_ros_lib/agent_setup.py
meili_ros_lib/config_agent.py
meili_ros_lib/connection.py
meili_ros_lib/docking.py
meili_ros_lib/maths.py
meili_ros_lib/offline.py
meili_ros_lib/parse_data.py
meili_ros_lib/sdk_handlers.py
meili_ros_lib/sentry.py
meili_ros_lib-0.1.3.dist-info/LICENSE.txt
meili_ros_lib-0.1.3.dist-info/METADATA
meili_ros_lib-0.1.3.dist-info/WHEEL
meili_ros_lib-0.1.3.dist-info/top_level.txt
meili_ros_lib-0.1.3.dist-info/RECORD
